misp_stix_converter/__init__.py
misp_stix_converter/misp2stix/__init__.py
misp_stix_converter/misp2stix/exportparser.py
misp_stix_converter/misp2stix/framing.py
misp_stix_converter/misp2stix/misp_to_stix1.py
misp_stix_converter/misp2stix/misp_to_stix2.py
misp_stix_converter/misp2stix/misp_to_stix20.py
misp_stix_converter/misp2stix/misp_to_stix21.py
misp_stix_converter/misp2stix/stix1_mapping.py
misp_stix_converter/misp2stix/stix20_mapping.py
misp_stix_converter/misp2stix/stix21_mapping.py
misp_stix_converter/misp2stix/stix2_mapping.py
misp_stix_converter/misp2stix/stix_mapping.py
misp_stix_converter/misp_stix_converter.py
misp_stix_converter/misp_stix_mapping.py
misp_stix_converter/stix2misp/__init__.py
misp_stix_converter/stix2misp/converters/__init__.py
misp_stix_converter/stix2misp/converters/stix2_attack_pattern_converter.py
misp_stix_converter/stix2misp/converters/stix2_campaign_converter.py
misp_stix_converter/stix2misp/converters/stix2_course_of_action_converter.py
misp_stix_converter/stix2misp/converters/stix2_custom_object_converter.py
misp_stix_converter/stix2misp/converters/stix2_identity_converter.py
misp_stix_converter/stix2misp/converters/stix2_indicator_converter.py
misp_stix_converter/stix2misp/converters/stix2_intrusion_set_converter.py
misp_stix_converter/stix2misp/converters/stix2_location_converter.py
misp_stix_converter/stix2misp/converters/stix2_malware_analysis_converter.py
misp_stix_converter/stix2misp/converters/stix2_malware_converter.py
misp_stix_converter/stix2misp/converters/stix2_note_converter.py
misp_stix_converter/stix2misp/converters/stix2_observable_converter.py
misp_stix_converter/stix2misp/converters/stix2_observable_objects_converter.py
misp_stix_converter/stix2misp/converters/stix2_observed_data_converter.py
misp_stix_converter/stix2misp/converters/stix2_threat_actor_converter.py
misp_stix_converter/stix2misp/converters/stix2_tool_converter.py
misp_stix_converter/stix2misp/converters/stix2_vulnerability_converter.py
misp_stix_custom-3.0.0.dist-info/LICENSE
misp_stix_custom-3.0.0.dist-info/METADATA
misp_stix_custom-3.0.0.dist-info/WHEEL
misp_stix_custom-3.0.0.dist-info/entry_points.txt
misp_stix_custom-3.0.0.dist-info/RECORD
