Metadata-Version: 2.1
Name: misp-stix-custom
Version: 3.0.0
Summary: Python scripts used by MISP to export MISP format into STIX and to import STIX into MISP format.
Home-page: https://github.com/MISP/misp-stix
License: BSD-3-Clause
Author: Christian Studer
Author-email: christian.studer@circl.lu
Maintainer: Christian Studer
Maintainer-email: christian.studer@circl.lu
Requires-Python: >=3.8,<4.0
Classifier: Development Status :: 4 - Beta
Classifier: Environment :: Console
Classifier: Intended Audience :: Information Technology
Classifier: Intended Audience :: Science/Research
Classifier: License :: OSI Approved :: BSD License
Classifier: Operating System :: POSIX :: Linux
Classifier: Programming Language :: Python :: 3
Classifier: Programming Language :: Python :: 3.8
Classifier: Programming Language :: Python :: 3.9
Classifier: Programming Language :: Python :: 3.10
Classifier: Programming Language :: Python :: 3.11
Classifier: Programming Language :: Python :: 3.12
Classifier: Topic :: Security
Requires-Dist: cybox (>=2.1.0,<3.0.0)
Requires-Dist: maec (>=4.1.0,<5.0.0)
Requires-Dist: misp-lib-stix2 (>=3.0.1,<4.0.0)
Requires-Dist: mixbox (>=1.0.3,<2.0.0)
Requires-Dist: pymisp (>=2.4.182,<3.0.0)
Requires-Dist: stix (>=1.2.0,<2.0.0)
Requires-Dist: stix-edh (==1.0.3)
Project-URL: Bug Tracker, https://github.com/MISP/misp-stix/issues
Project-URL: Documentation, https://misp.github.io/misp-stix/
Project-URL: Repository, https://github.com/MISP/misp-stix
Project-URL: Source, https://github.com/MISP/misp-stix
